sussh/__init__.py
sussh/core.py
itssussh-4.3.0.dist-info/METADATA
itssussh-4.3.0.dist-info/WHEEL
itssussh-4.3.0.dist-info/entry_points.txt
itssussh-4.3.0.dist-info/top_level.txt
itssussh-4.3.0.dist-info/RECORD
