Metadata-Version: 2.4
Name: itssussh
Version: 4.3.0
Summary:  SVPS WebSocket Client
Author: Eternals
Requires-Dist: websocket-client>=1.6.0
Dynamic: author
Dynamic: requires-dist
Dynamic: summary
